pyecharts_snapshot/__init__.py
pyecharts_snapshot/logger.py
pyecharts_snapshot/main.py
pyecharts_snapshot/phantomjs/snapshot.js
pyecharts_snapshot-0.2.0.dist-info/METADATA
pyecharts_snapshot-0.2.0.dist-info/WHEEL
pyecharts_snapshot-0.2.0.dist-info/entry_points.txt
pyecharts_snapshot-0.2.0.dist-info/top_level.txt
pyecharts_snapshot-0.2.0.dist-info/RECORD
