Metadata-Version: 1.1
Name: pyecharts-snapshot
Version: 0.2.0
Summary: renders pyecharts output as image
Home-page: https://github.com/pyecharts/pyecharts-snapshot
Author: pyecharts dev team
Author-email: info@pyecharts.com
License: MIT
Download-URL: https://github.com/pyecharts/pyecharts-snapshot/archive/0.2.0.tar.gz
Keywords: python,echarts,visualisation,data,utility,png,jpeg,svg,pdf
Platform: UNKNOWN
Classifier: Topic :: Software Development :: Libraries
Classifier: Programming Language :: Python
Classifier: Intended Audience :: Developers
Classifier: Programming Language :: Python :: 3 :: Only
Classifier: Programming Language :: Python :: 3.5
Classifier: Programming Language :: Python :: 3.6
Classifier: Programming Language :: Python :: 3.7
Classifier: Programming Language :: Python :: 3.8
